README.md
setup.py
dis_upload/Binomialdistribution.py
dis_upload/Gaussiandistribution.py
dis_upload/Generaldistribution.py
dis_upload/__init__.py
dis_upload.egg-info/PKG-INFO
dis_upload.egg-info/SOURCES.txt
dis_upload.egg-info/dependency_links.txt
dis_upload.egg-info/not-zip-safe
dis_upload.egg-info/top_level.txt