Metadata-Version: 1.0
Name: dis-upload
Version: 0.2
Summary: Gaussian and Binomail distributions
Home-page: UNKNOWN
Author: Padej R
Author-email: rpadej@yahoo.com
License: UNKNOWN
Platform: UNKNOWN
